fig2latex/__init__.py
fig2latex/fig2latex.py
fig2latex-0.0.1.dist-info/LICENSE
fig2latex-0.0.1.dist-info/METADATA
fig2latex-0.0.1.dist-info/WHEEL
fig2latex-0.0.1.dist-info/top_level.txt
fig2latex-0.0.1.dist-info/RECORD
