Metadata-Version: 2.1
Name: fig2latex
Version: 0.0.1
Summary: fig2latex is a Python utility for converting figures to LaTeX format. This utility simplifies the process of including figures in LaTeX documents by generating the necessary LaTeX code.
Home-page: https://github.com/Tesla2000/seriattrs
Author: Tesla2000
Author-email: fratajczak124@gmail.com
Project-URL: Homepage, https://github.com/Tesla2000/seriattrs
Classifier: Programming Language :: Python :: 3
Classifier: License :: OSI Approved :: MIT License
Classifier: Operating System :: OS Independent
Requires-Python: >=3.5
License-File: LICENSE
